{
    "Author": "ALLINONE_REBORN",
    "Telegram_channel": "https://t.me/allinone_reborn",
    "name": "FanCode Live Matches API",
    "last_updated": "11:10:50 AM 17-12-2025",
    "headers": {
        "User-Agent": "ReactNativeVideo/7.19.1 (Linux;Android/13) AndroidXMedia3/1.1.1",
        "Referer": "https://fancode.com/"
    },
    "total_live_matches": 2,
    "matches": [
        {
            "category": "Cricket",
            "match_id": 138910,
            "title": "General Education Academy Vs Al Barkat",
            "tournament": "129th Harris Shield Cricket Tournament",
            "status": "LIVE",
            "streamingStatus": "STARTED",
            "image": "https://www.fancode.com/skillup-uploads/cms-media/129th-Harris-Shield-Cricket-Tournament-old-match-card_v2.jpg",
            "India": "https://in-mc-fdlive.fancode.com/mumbai/138910_english_hls_ea9fe29d8e15886_1ta-di_h264/index.m3u8",
            "Worldwide": "https://allinonereborn.fun/fc/play.php?url=https://in-mc-fdlive.fancode.com/mumbai/138910_english_hls_ea9fe29d8e15886_1ta-di_h264/index.m3u8"
        },
        {
            "category": "Cricket",
            "match_id": 138911,
            "title": "Anjuman English Allana Vs Dyandeep Seva Mandal",
            "tournament": "129th Harris Shield Cricket Tournament",
            "status": "LIVE",
            "streamingStatus": "STARTED",
            "image": "https://www.fancode.com/skillup-uploads/cms-media/129th-Harris-Shield-Cricket-Tournament-old-match-card_v2.jpg",
            "India": "https://in-mc-fdlive.fancode.com/mumbai/138911_english_hls_465e4ec22219894_1ta-di_h264/index.m3u8",
            "Worldwide": "https://allinonereborn.fun/fc/play.php?url=https://in-mc-fdlive.fancode.com/mumbai/138911_english_hls_465e4ec22219894_1ta-di_h264/index.m3u8"
        }
    ]
}