[
  {
    "channelNumber": 142549,
    "linkType": "app",
    "platform": "FanCode",
    "channelName": "JAP vs TAU",
    "subText": "Live Streaming Now",
    "startTime": "",
    "drm_licence": "",
    "ownerInfo": "Stream provided by public source",
    "thumbnail": "https://images.fancode.com/aig/match/v1778855488829/142549_CASACARDS_APP.png",
    "channelUrl": "https://in-mc-fblive.fancode.com/mumbai/142549_english_hls_886af6db9310477_1ta-di_h264/index.m3u8",
    "match_id": 142549,
    "category": "football"
  },
  {
    "channelNumber": 140505,
    "linkType": "app",
    "platform": "FanCode",
    "channelName": "MSC vs MCF",
    "subText": "Live Streaming Now",
    "startTime": "",
    "drm_licence": "",
    "ownerInfo": "Stream provided by public source",
    "thumbnail": "https://www.fancode.com/skillup-uploads/cms-media/140505_5956_MSC_MCFC_FC-Web_1772473605941.jpg",
    "channelUrl": "https://in-mc-fblive.fancode.com/mumbai/140505_english_hls_828346785262853_1ta-di_h264/index.m3u8",
    "match_id": 140505,
    "category": "football"
  },
  {
    "channelNumber": 70,
    "platform": "FanCode",
    "linkType": "app",
    "channelName": "Football Stream 1",
    "subText": "Live Streaming Now",
    "startTime": "",
    "ownerInfo": "Stream provided by public source",
    "channelUrl": "https://dmitwlvvll.cdn.mangomolo.com/dubaisportshd/smil:dubaisportshd.smil/index.m3u8",
    "thumbnail": "https://gitlab.com/ranginfotech89/ipl_data_api/-/raw/main/stream_categories/cricket_league_vectors/football_new.png"
  }
]