[
  {
    "channelNumber": 141449,
    "linkType": "app",
    "platform": "FanCode",
    "channelName": "Server 10",
    "subText": "Live tv guide",
    "startTime": "",
    "drm_licence": "",
    "ownerInfo": "Stream provided by public source",
    "thumbnail": "https://www.fancode.com/skillup-uploads/cms-media/Uganda-tour-of-Namibia-2026_Web_1080_x_810.jpg",
    "channelUrl": "https://in-mc-flive.fancode.com/mumbai/141449_english_hls_2b45087d4a92556_1ta-di_h264/index.m3u8",
    "match_id": 141449
  },
  {
    "channelNumber": 1090508036,
    "linkType": "app",
    "platform": "SonyLiv",
    "channelName": "Server 9",
    "subText": "Live Streaming Now",
    "startTime": "",
    "drm_licence": "",
    "ownerInfo": "Stream provided by public source",
    "thumbnail": "https://origin-staticv2.sonyliv.com/videoasset_images/manage_file/1000016576/1774436373190422_IFC_Rajasthan_United_FC-vs-Chanmari_FC_landscape_thumb.jpg",
    "channelUrl": "https://sonydaimenew.akamaized.net/hls/live/20000293/IFL_Raja0104/ENG/std_lrh-800300010.m3u8?hdnea=exp=1775088144~acl=/*~id=55813681063908313099559114814066~hmac=244ee1c592e625bbd081be8376d2e7a73d11872b4c4f4f92e58fd6e34861f782",
    "match_id": "1090508036_ENG"
  },
  {
    "channelNumber": 1389,
    "platform": "CricHD",
    "linkType": "app",
    "channelName": "Server 8",
    "subText": "Live tv guide",
    "startTime": "",
    "ownerInfo": "Stream provided by public source",
    "channelUrl": "https://n2.zohanayaan.com:1686/hls/willowusa.m3u8?md5=z6gS4mV_ToEuwSkU2lNDFA&expires=1775048163",
    "thumbnail": "https://gitlab.com/ranginfotech89/ipl_data_api/-/raw/main/stream_categories/cricket_league_vectors/all_live_streaming_inonly.png"
  },
  {
    "channelNumber": 5535,
    "platform": "CricHD",
    "linkType": "app",
    "channelName": "Server 7",
    "subText": "Live tv guide",
    "startTime": "",
    "ownerInfo": "Stream provided by public source",
    "channelUrl": "https://n4.zohanayaan.com:1686/hls/star1in.m3u8?md5=dpp1E3rJWCWUYBXpgNrl1w&expires=1775048162",
    "thumbnail": "https://gitlab.com/ranginfotech89/ipl_data_api/-/raw/main/stream_categories/cricket_league_vectors/all_live_streaming_inonly.png"
  },
  {
    "channelNumber": 70,
    "platform": "FanCode",
    "linkType": "web",
    "channelName": "Server 6",
    "subText": "Live tv guide",
    "startTime": "",
    "ownerInfo": "Stream provided by public source",
    "channelUrl": "",
    "thumbnail": "https://gitlab.com/ranginfotech89/ipl_data_api/-/raw/main/stream_categories/cricket_league_vectors/all_live_streaming_inonly.png"
  },
  {
    "channelNumber": 70,
    "platform": "FanCode",
    "linkType": "web",
    "channelName": "Server 5",
    "subText": "Live tv guide",
    "startTime": "",
    "ownerInfo": "Stream provided by public source",
    "channelUrl": "",
    "thumbnail": "https://gitlab.com/ranginfotech89/ipl_data_api/-/raw/main/stream_categories/cricket_league_vectors/all_live_streaming_inonly.png"
  },
  {
    "channelNumber": 70,
    "platform": "FanCode",
    "linkType": "web",
    "channelName": "Server 4",
    "subText": "Live tv guide",
    "startTime": "",
    "ownerInfo": "Stream provided by public source",
    "channelUrl": "",
    "thumbnail": "https://gitlab.com/ranginfotech89/ipl_data_api/-/raw/main/stream_categories/cricket_league_vectors/all_live_streaming_inonly.png"
  },
  {
    "channelNumber": 70,
    "platform": "FanCode",
    "linkType": "web",
    "channelName": "Server 3",
    "subText": "Live tv guide",
    "startTime": "",
    "ownerInfo": "Stream provided by public source",
    "channelUrl": "",
    "thumbnail": "https://gitlab.com/ranginfotech89/ipl_data_api/-/raw/main/stream_categories/cricket_league_vectors/all_live_streaming_inonly.png"
  },
  {
    "channelNumber": 70,
    "platform": "FanCode",
    "linkType": "web",
    "channelName": "Server 2",
    "subText": "Live tv guide",
    "startTime": "",
    "ownerInfo": "Stream provided by public source",
    "channelUrl": "",
    "thumbnail": "https://gitlab.com/ranginfotech89/ipl_data_api/-/raw/main/stream_categories/cricket_league_vectors/all_live_streaming_inonly.png"
  },
  {
    "channelNumber": 70,
    "platform": "FanCode",
    "linkType": "web",
    "channelName": "Server 1",
    "subText": "Live tv guide",
    "startTime": "",
    "ownerInfo": "Stream provided by public source",
    "channelUrl": "",
    "thumbnail": "https://gitlab.com/ranginfotech89/ipl_data_api/-/raw/main/stream_categories/cricket_league_vectors/all_live_streaming_inonly.png"
  }
]