[
  {
    "channelNumber": 1090499953,
    "linkType": "app",
    "platform": "SonyLiv",
    "channelName": "Server 16",
    "subText": "Live Streaming Now",
    "startTime": "",
    "drm_licence": "",
    "ownerInfo": "Stream provided by public source",
    "thumbnail": "https://origin-staticv2.sonyliv.com/videoasset_images/manage_file/1000013020/1767675889403714_SuperSmash2526_womens_Wellington_Blaze_vs_Canterbury_Magicians_6jan_landscape_thumb.jpg",
    "channelUrl": "https://sonydaimenew.akamaized.net/hls/live/2105080/DAI24ME-V3/std_lrh-800300010.m3u8?hdnea=exp=1768822854~acl=/*~id=24538660833780739623599213012737~hmac=20a9474055d6a89a3c1d84edbce8e4c0faf67ed1f6c80b0c45c1182a1877037c",
    "match_id": "1090499953_ENG"
  },
  {
    "channelNumber": 138785,
    "linkType": "app",
    "platform": "FanCode",
    "channelName": "Server 15",
    "subText": "Live tv guide",
    "startTime": "",
    "drm_licence": "",
    "ownerInfo": "Stream provided by public source",
    "thumbnail": "https://www.fancode.com/skillup-uploads/cms-media/138785_5801_WB-W_CM-W_fc-web_1766596522099.jpg",
    "channelUrl": "https://in-mc-fdlive.fancode.com/mumbai/138785_english_hls_e707acb86e77540_1ta-di_h264/index.m3u8",
    "match_id": 138785
  },
  {
    "channelNumber": 1389,
    "platform": "CricHD",
    "linkType": "app",
    "channelName": "Server 14",
    "subText": "Live tv guide",
    "startTime": "",
    "ownerInfo": "Stream provided by public source",
    "channelUrl": "https://d10.merichunidya.com:1686/hls/willowusa.m3u8?md5=vWYBJRT8WG04xi3b2G50Kg&expires=1768785588",
    "thumbnail": "https://gitlab.com/ranginfotech89/ipl_data_api/-/raw/main/stream_categories/cricket_league_vectors/all_live_streaming_inonly.png"
  },
  {
    "channelNumber": 5535,
    "platform": "CricHD",
    "linkType": "app",
    "channelName": "Server 13",
    "subText": "Live tv guide",
    "startTime": "",
    "ownerInfo": "Stream provided by public source",
    "channelUrl": "https://d3.merichunidya.com:1686/hls/star1in.m3u8?md5=PmwESd-BU_cHFxaYv-GPJQ&expires=1768785587",
    "thumbnail": "https://gitlab.com/ranginfotech89/ipl_data_api/-/raw/main/stream_categories/cricket_league_vectors/all_live_streaming_inonly.png"
  },
  {
    "channelNumber": 70,
    "platform": "FanCode",
    "linkType": "web",
    "channelName": "Server 12",
    "subText": "Live tv guide",
    "startTime": "",
    "ownerInfo": "Stream provided by public source",
    "channelUrl": "",
    "thumbnail": "https://gitlab.com/ranginfotech89/ipl_data_api/-/raw/main/stream_categories/cricket_league_vectors/all_live_streaming_inonly.png"
  },
  {
    "channelNumber": 70,
    "platform": "FanCode",
    "linkType": "web",
    "channelName": "Server 11",
    "subText": "Live tv guide",
    "startTime": "",
    "ownerInfo": "Stream provided by public source",
    "channelUrl": "",
    "thumbnail": "https://gitlab.com/ranginfotech89/ipl_data_api/-/raw/main/stream_categories/cricket_league_vectors/all_live_streaming_inonly.png"
  },
  {
    "channelNumber": 70,
    "platform": "FanCode",
    "linkType": "web",
    "channelName": "Server 10",
    "subText": "Live tv guide",
    "startTime": "",
    "ownerInfo": "Stream provided by public source",
    "channelUrl": "",
    "thumbnail": "https://gitlab.com/ranginfotech89/ipl_data_api/-/raw/main/stream_categories/cricket_league_vectors/all_live_streaming_inonly.png"
  },
  {
    "channelNumber": 70,
    "platform": "FanCode",
    "linkType": "web",
    "channelName": "Server 9",
    "subText": "Live tv guide",
    "startTime": "",
    "ownerInfo": "Stream provided by public source",
    "channelUrl": "",
    "thumbnail": "https://gitlab.com/ranginfotech89/ipl_data_api/-/raw/main/stream_categories/cricket_league_vectors/all_live_streaming_inonly.png"
  },
  {
    "channelNumber": 70,
    "platform": "FanCode",
    "linkType": "web",
    "channelName": "Server 8",
    "subText": "Live tv guide",
    "startTime": "",
    "ownerInfo": "Stream provided by public source",
    "channelUrl": "",
    "thumbnail": "https://gitlab.com/ranginfotech89/ipl_data_api/-/raw/main/stream_categories/cricket_league_vectors/all_live_streaming_inonly.png"
  },
  {
    "channelNumber": 70,
    "platform": "FanCode",
    "linkType": "app",
    "channelName": "Server 7",
    "subText": "Live tv guide",
    "startTime": "",
    "ownerInfo": "Stream provided by public source",
    "channelUrl": "",
    "thumbnail": "https://gitlab.com/ranginfotech89/ipl_data_api/-/raw/main/stream_categories/cricket_league_vectors/all_live_streaming_inonly.png"
  },
  {
    "channelNumber": 70,
    "platform": "FanCode",
    "linkType": "web",
    "channelName": "Server 6",
    "subText": "Live tv guide",
    "startTime": "",
    "ownerInfo": "Stream provided by public source",
    "channelUrl": "",
    "thumbnail": "https://gitlab.com/ranginfotech89/ipl_data_api/-/raw/main/stream_categories/cricket_league_vectors/all_live_streaming_inonly.png"
  },
  {
    "channelNumber": 70,
    "platform": "FanCode",
    "linkType": "web",
    "channelName": "Server 5",
    "subText": "Live tv guide",
    "startTime": "",
    "ownerInfo": "Stream provided by public source",
    "channelUrl": "",
    "thumbnail": "https://gitlab.com/ranginfotech89/ipl_data_api/-/raw/main/stream_categories/cricket_league_vectors/all_live_streaming_inonly.png"
  },
  {
    "channelNumber": 70,
    "platform": "FanCode",
    "linkType": "web",
    "channelName": "Server 4",
    "subText": "Live tv guide",
    "startTime": "",
    "ownerInfo": "Stream provided by public source",
    "channelUrl": "",
    "thumbnail": "https://gitlab.com/ranginfotech89/ipl_data_api/-/raw/main/stream_categories/cricket_league_vectors/all_live_streaming_inonly.png"
  },
  {
    "channelNumber": 70,
    "platform": "FanCode",
    "linkType": "web",
    "channelName": "Server 3",
    "subText": "Live tv guide",
    "startTime": "",
    "ownerInfo": "Stream provided by public source",
    "channelUrl": "",
    "thumbnail": "https://gitlab.com/ranginfotech89/ipl_data_api/-/raw/main/stream_categories/cricket_league_vectors/all_live_streaming_inonly.png"
  },
  {
    "channelNumber": 70,
    "platform": "FanCode",
    "linkType": "web",
    "channelName": "Server 2",
    "subText": "Live tv guide",
    "startTime": "",
    "ownerInfo": "Stream provided by public source",
    "channelUrl": "",
    "thumbnail": "https://gitlab.com/ranginfotech89/ipl_data_api/-/raw/main/stream_categories/cricket_league_vectors/all_live_streaming_inonly.png"
  },
  {
    "channelNumber": 70,
    "platform": "FanCode",
    "linkType": "web",
    "channelName": "Server 1",
    "subText": "Live tv guide",
    "startTime": "",
    "ownerInfo": "Stream provided by public source",
    "channelUrl": "",
    "thumbnail": "https://gitlab.com/ranginfotech89/ipl_data_api/-/raw/main/stream_categories/cricket_league_vectors/all_live_streaming_inonly.png"
  }
]