[
  {
    "channelNumber": 139922,
    "linkType": "app",
    "platform": "FanCode",
    "channelName": "ML vs ILJ",
    "subText": "Live Streaming Now",
    "startTime": "",
    "drm_licence": "",
    "ownerInfo": "Stream provided by public source",
    "thumbnail": "https://www.fancode.com/skillup-uploads/cms-media/Juego-de-leyendas_web.jpg",
    "channelUrl": "https://in-mc-fdlive.fancode.com/mumbai/139922_english_hls_a70226954d38569_1ta-di_h264/index.m3u8",
    "match_id": 139922,
    "category": "football"
  },
  {
    "channelNumber": 70,
    "platform": "FanCode",
    "linkType": "app",
    "channelName": "Football Stream 1",
    "subText": "Live Streaming Now",
    "startTime": "",
    "ownerInfo": "Stream provided by public source",
    "channelUrl": "https://dmitwlvvll.cdn.mangomolo.com/dubaisportshd/smil:dubaisportshd.smil/index.m3u8",
    "thumbnail": "https://gitlab.com/ranginfotech89/ipl_data_api/-/raw/main/stream_categories/cricket_league_vectors/football_new.png"
  }
]