[
  {
    "channelNumber": 1090506607,
    "linkType": "app",
    "platform": "SonyLiv",
    "channelName": "Bundesliga 2025-26",
    "subText": "Live Streaming Now",
    "startTime": "",
    "drm_licence": "",
    "ownerInfo": "Stream provided by public source",
    "thumbnail": "https://origin-staticv2.sonyliv.com/videoasset_images/manage_file/1000016185/1773483212603469_bliga26_MD26_Hamburg_SV_vs_FC_Koln_14mar_landscape_thumb.jpg",
    "channelUrl": "https://sonydaimenew.akamaized.net/hls/live/2022317/DAI13ME-V3/std_lrh-800300010.m3u8?hdnea=exp=1773554850~acl=/*~id=70535583653730581214677094007053~hmac=f03b54633f1400e837a788b73d43cf06c12e11f765378038987e17008ff61f72",
    "match_id": "1090506607_ENG",
    "category": "football"
  },
  {
    "channelNumber": 141220,
    "linkType": "app",
    "platform": "FanCode",
    "channelName": "RZ vs ALH",
    "subText": "Live Streaming Now",
    "startTime": "",
    "drm_licence": "",
    "ownerInfo": "Stream provided by public source",
    "thumbnail": "https://images.fancode.com/aig/match/v1773431102733/141220_CASACARDS_APP.png",
    "channelUrl": "https://in-mc-fdlive.fancode.com/mumbai/141220_english_hls_8165071ae751937_1ta-di_h264/index.m3u8",
    "match_id": 141220,
    "category": "football"
  },
  {
    "channelNumber": 131108,
    "linkType": "app",
    "platform": "FanCode",
    "channelName": "RO vs VCL",
    "subText": "Live Streaming Now",
    "startTime": "",
    "drm_licence": "",
    "ownerInfo": "Stream provided by public source",
    "thumbnail": "https://www.fancode.com/skillup-uploads/cms-media/131108_5427_RO_VAL_FC-Web.png",
    "channelUrl": "https://in-mc-fdlive.fancode.com/mumbai/131108_english_hls_ad236bef6a87088_1ta-di_h264/index.m3u8",
    "match_id": 131108,
    "category": "football"
  },
  {
    "channelNumber": 70,
    "platform": "FanCode",
    "linkType": "app",
    "channelName": "Football Stream 1",
    "subText": "Live Streaming Now",
    "startTime": "",
    "ownerInfo": "Stream provided by public source",
    "channelUrl": "https://dmitwlvvll.cdn.mangomolo.com/dubaisportshd/smil:dubaisportshd.smil/index.m3u8",
    "thumbnail": "https://gitlab.com/ranginfotech89/ipl_data_api/-/raw/main/stream_categories/cricket_league_vectors/football_new.png"
  }
]