[
  {
    "channelNumber": 1090499541,
    "linkType": "app",
    "platform": "SonyLiv",
    "channelName": "Bundesliga 2025-26",
    "subText": "Live Streaming Now",
    "startTime": "",
    "drm_licence": "",
    "ownerInfo": "Stream provided by public source",
    "thumbnail": "https://origin-staticv2.sonyliv.com/videoasset_images/manage_file/1000013251/1768136708974648_bliga26_MD17_VfL_Wolfsburg_vs_St_Pauli_11jan_landscape_thumb.jpg",
    "channelUrl": "https://sonydaimenew.akamaized.net/hls/live/2094589/DAI05ME-V3/std_lrh-800300010.m3u8?hdnea=exp=1768459114~acl=/*~id=44245117814293561756426859745598~hmac=fd31da7540ebf2765e7f73f10c6dea6c20ce6e64584f6a71c0dfbfaedcc55634",
    "match_id": "1090499541_ENG",
    "category": "football"
  },
  {
    "channelNumber": 139359,
    "linkType": "app",
    "platform": "FanCode",
    "channelName": "ASF vs ATR",
    "subText": "Live Streaming Now",
    "startTime": "",
    "drm_licence": "",
    "ownerInfo": "Stream provided by public source",
    "thumbnail": "https://www.fancode.com/skillup-uploads/cms-media/Al-Ahli-Saudi-vs-Al-Taawoun_Web.jpg",
    "channelUrl": "https://in-mc-fdlive.fancode.com/mumbai/139359_english_hls_7a1b5dc1bf4570_1ta-di_h264/index.m3u8",
    "match_id": 139359,
    "category": "football"
  },
  {
    "channelNumber": 138391,
    "linkType": "app",
    "platform": "FanCode",
    "channelName": "SEN vs EAC",
    "subText": "Live Streaming Now",
    "startTime": "",
    "drm_licence": "",
    "ownerInfo": "Stream provided by public source",
    "thumbnail": "https://www.fancode.com/skillup-uploads/cms-media/Senegal-vs-Egypt_fc-web.jpg",
    "channelUrl": "https://in-mc-fdlive.fancode.com/mumbai/138391_english_hls_468a4aabcc41921_1ta-di_h264/index.m3u8",
    "match_id": 138391,
    "category": "football"
  },
  {
    "channelNumber": 70,
    "platform": "FanCode",
    "linkType": "app",
    "channelName": "Football Stream 1",
    "subText": "Live Streaming Now",
    "startTime": "",
    "ownerInfo": "Stream provided by public source",
    "channelUrl": "https://dmitwlvvll.cdn.mangomolo.com/dubaisportshd/smil:dubaisportshd.smil/index.m3u8",
    "thumbnail": "https://gitlab.com/ranginfotech89/ipl_data_api/-/raw/main/stream_categories/cricket_league_vectors/football_new.png"
  }
]