[
  {
    "channelNumber": 1090491616,
    "linkType": "app",
    "platform": "SonyLiv",
    "channelName": "Bundesliga 2025-26 - Football",
    "subText": "Live Streaming Now",
    "startTime": "",
    "drm_licence": "",
    "ownerInfo": "Stream provided by public source",
    "thumbnail": "https://origin-staticv2.sonyliv.com/videoasset_images/manage_file/1000009802/175945492122489_bliga2526_MD6_Frankfurt_vs_Bayern_2oct_landscape_thumb.jpg",
    "channelUrl": "https://liveakmt-p-web.slivcdn.com/hls/live/2022317/DAI13ME-V3/std_lrh-800300010.m3u8?hdnea=exp=1759645636~acl=/*~id=81820389718918212205502283832199~hmac=52136fe8631cc3400ada4286ef65f5b4df8fa19e69f0da4e6a0053d59d6e63fe",
    "match_id": "1090491616_ENG"
  },
  {
    "channelNumber": 130903,
    "linkType": "app",
    "platform": "FanCode",
    "channelName": "RM vs VCF - L - Football",
    "subText": "Live tv guide",
    "startTime": "",
    "drm_licence": "",
    "ownerInfo": "Stream provided by public source",
    "thumbnail": "https://www.fancode.com/skillup-uploads/cms-media/130903_5427_RM_VIL_fc-Web.jpg",
    "channelUrl": "https://in-mc-fdlive.fancode.com/mumbai/130903_bengali_hls_1769fbe90158531adfreeta-di_h264/index.m3u8",
    "match_id": 130903
  },
  {
    "channelNumber": 130903,
    "linkType": "app",
    "platform": "FanCode",
    "channelName": "RM vs VCF - L - Hindi - Football",
    "subText": "Live tv guide",
    "startTime": "",
    "drm_licence": "",
    "ownerInfo": "Stream provided by public source",
    "thumbnail": "https://www.fancode.com/skillup-uploads/cms-media/130903_5427_RM_VIL_fc-Web.jpg",
    "channelUrl": "https://in-mc-fdlive.fancode.com/mumbai/130903_hindi_hls_3f147dcba151412adfreeta-di_h264/index.m3u8",
    "match_id": 130903
  },
  {
    "channelNumber": 130903,
    "linkType": "app",
    "platform": "FanCode",
    "channelName": "RM vs VCF - L - Football",
    "subText": "Live tv guide",
    "startTime": "",
    "drm_licence": "",
    "ownerInfo": "Stream provided by public source",
    "thumbnail": "https://www.fancode.com/skillup-uploads/cms-media/130903_5427_RM_VIL_fc-Web.jpg",
    "channelUrl": "https://in-mc-fdlive.fancode.com/mumbai/130903_english_hls_7acae660d754143adfreeta-di_h264/index.m3u8",
    "match_id": 130903
  },
  {
    "channelNumber": 130901,
    "linkType": "app",
    "platform": "FanCode",
    "channelName": "ACL vs RML - - Football",
    "subText": "Live tv guide",
    "startTime": "",
    "drm_licence": "",
    "ownerInfo": "Stream provided by public source",
    "thumbnail": "https://www.fancode.com/skillup-uploads/cms-media/130901_5427_ATH_MRC_fc-Web.jpg",
    "channelUrl": "https://in-mc-fdlive.fancode.com/mumbai/130901_english_hls_0a159a5fc337141adfreeta-di_h264/index.m3u8",
    "match_id": 130901
  },
  {
    "channelNumber": 70,
    "platform": "FanCode",
    "linkType": "web",
    "channelName": "Watch link",
    "subText": "Live tv guide",
    "startTime": "",
    "ownerInfo": "Stream provided by public source",
    "channelUrl": "https://t.me/crickly",
    "thumbnail": "https://gitlab.com/ranginfotech89/ipl_data_api/-/raw/main/stream_categories/cricket_league_vectors/all_live_streaming_inonly.png"
  }
]