[
  {
    "channelNumber": 1090491166,
    "linkType": "app",
    "platform": "SonyLiv",
    "channelName": "UEFA Champions League 2025-26",
    "subText": "Live Streaming Now",
    "startTime": "",
    "drm_licence": "",
    "ownerInfo": "Stream provided by public source",
    "thumbnail": "https://origin-staticv2.sonyliv.com/videoasset_images/manage_file/1000009239/1758102638377870_UCL26_MD2_Atalanta_vs_Club-Brugge_landscape_thumb.jpg",
    "channelUrl": "https://liveakmt-p-web.slivcdn.com/hls/live/2037143/DAI23ME-V3/std_lrh-800300010.m3u8?hdnea=exp=1759296255~acl=/*~id=76931708812432274277756617649875~hmac=2417aec3499c7f3d11ede8f0e55685efc6fd65b4774dccb5351571ada74fed85",
    "match_id": "1090491166_ENG",
    "category": "football"
  },
  {
    "channelNumber": 1090491165,
    "linkType": "app",
    "platform": "SonyLiv",
    "channelName": "UEFA Champions League 2025-26",
    "subText": "Live Streaming Now",
    "startTime": "",
    "drm_licence": "",
    "ownerInfo": "Stream provided by public source",
    "thumbnail": "https://origin-staticv2.sonyliv.com/videoasset_images/manage_file/1000008656/1758105862425656_UCL26_MD1_KairatAlmaty_vs_Real_Madrid_landscape_thumb.jpg",
    "channelUrl": "https://liveakmt-p-web.slivcdn.com/hls/live/2018458/DAI10ME-V3/std_lrh-800300010.m3u8?hdnea=exp=1759296255~acl=/*~id=76931708812432274277756617649875~hmac=2417aec3499c7f3d11ede8f0e55685efc6fd65b4774dccb5351571ada74fed85",
    "match_id": "1090491165_ENG",
    "category": "football"
  },
  {
    "channelNumber": 136053,
    "linkType": "app",
    "platform": "FanCode",
    "channelName": "ASA vs SAC",
    "subText": "Live Streaming Now",
    "startTime": "",
    "drm_licence": "",
    "ownerInfo": "Stream provided by public source",
    "thumbnail": "https://www.fancode.com/skillup-uploads/cms-media/136053_5647_SDD_SHJ_fc-Web.jpg",
    "channelUrl": "http://147.93.107.176:8080/fancode/mumbai/136053_english_hls_61a3f686dd24071ta-di_h264/index.m3u8",
    "match_id": 136053,
    "category": "football"
  },
  {
    "channelNumber": 70,
    "platform": "FanCode",
    "linkType": "app",
    "channelName": "Football Stream 1",
    "subText": "Live Streaming Now",
    "startTime": "",
    "ownerInfo": "Stream provided by public source",
    "channelUrl": "https://dmitwlvvll.cdn.mangomolo.com/dubaisportshd/smil:dubaisportshd.smil/index.m3u8",
    "thumbnail": "https://gitlab.com/ranginfotech89/ipl_data_api/-/raw/main/stream_categories/cricket_league_vectors/football_new.png"
  }
]