[
  {
    "channelNumber": 1090507517,
    "linkType": "app",
    "platform": "SonyLiv",
    "channelName": "Indian Football League 2026",
    "subText": "Live Streaming Now",
    "startTime": "",
    "drm_licence": "",
    "ownerInfo": "Stream provided by public source",
    "thumbnail": "https://origin-staticv2.sonyliv.com/videoasset_images/manage_file/1000016478/17741598426996_IFC_Rajasthan_United_FC-vs-Diamond_Harbour_FC_landscape_thumb.jpg",
    "channelUrl": "https://sonydaimenew.akamaized.net/hls/live/20000099/Rajastha2603/ENG/std_lrh-800300010.m3u8?hdnea=exp=1774569688~acl=/*~id=81994063269889618755667461622489~hmac=2ad09028f289ab5ac406bcc8f8e7795f47e06ff0bdf5694e5e1d3227be6bd38c",
    "match_id": "1090507517_ENG",
    "category": "football"
  },
  {
    "channelNumber": 70,
    "platform": "FanCode",
    "linkType": "app",
    "channelName": "Football Stream 1",
    "subText": "Live Streaming Now",
    "startTime": "",
    "ownerInfo": "Stream provided by public source",
    "channelUrl": "https://dmitwlvvll.cdn.mangomolo.com/dubaisportshd/smil:dubaisportshd.smil/index.m3u8",
    "thumbnail": "https://gitlab.com/ranginfotech89/ipl_data_api/-/raw/main/stream_categories/cricket_league_vectors/football_new.png"
  }
]