[
  {
    "channelNumber": 1090506963,
    "linkType": "app",
    "platform": "SonyLiv",
    "channelName": "Indian Football League 2026",
    "subText": "Live Streaming Now",
    "startTime": "",
    "drm_licence": "",
    "ownerInfo": "Stream provided by public source",
    "thumbnail": "https://origin-staticv2.sonyliv.com/videoasset_images/manage_file/1000016248/1773648580399805_IFC_Chanmari_FC-vs-Shillong_Lajong_FC_landscape_thumb.jpg",
    "channelUrl": "https://sonydaimenew.akamaized.net/hls/live/2037143/DAI23ME-V3/std_lrh-800300010.m3u8?hdnea=exp=1773960855~acl=/*~id=06393609866961126357712998951386~hmac=82a8d825bf8630c865fe7c2d279c99a3149354b78d4053f4430773114fb5905f",
    "match_id": "1090506963_ENG",
    "category": "football"
  },
  {
    "channelNumber": 140819,
    "linkType": "app",
    "platform": "FanCode",
    "channelName": "CTW vs DKW - AWAC 2026",
    "subText": "Live Streaming Now",
    "startTime": "",
    "drm_licence": "",
    "ownerInfo": "Stream provided by public source",
    "thumbnail": "https://www.fancode.com/skillup-uploads/cms-media/140819_5979_TPE-W_NK-W_fc-Web.jpg",
    "channelUrl": "https://in-mc-flive.fancode.com/mumbai/140819_english_hls_50652d189c5112_1ta-di_h264/index.m3u8",
    "match_id": 140819,
    "category": "football"
  },
  {
    "channelNumber": 70,
    "platform": "FanCode",
    "linkType": "app",
    "channelName": "Football Stream 1",
    "subText": "Live Streaming Now",
    "startTime": "",
    "ownerInfo": "Stream provided by public source",
    "channelUrl": "https://dmitwlvvll.cdn.mangomolo.com/dubaisportshd/smil:dubaisportshd.smil/index.m3u8",
    "thumbnail": "https://gitlab.com/ranginfotech89/ipl_data_api/-/raw/main/stream_categories/cricket_league_vectors/football_new.png"
  }
]