[
  {
    "channelNumber": 137304,
    "linkType": "app",
    "platform": "FanCode",
    "channelName": "NYL vs HGC",
    "subText": "Live tv guide",
    "startTime": "",
    "drm_licence": "",
    "ownerInfo": "Stream provided by public source",
    "thumbnail": "https://images.fancode.com/aig/match/v1/137304_CASACARDS_APP.png",
    "channelUrl": "https://in-mc-fdlive.fancode.com/mumbai/137304_english_hls_fed31b602d66901ta-di_h264/index.m3u8",
    "match_id": 137304
  },
  {
    "channelNumber": 137303,
    "linkType": "app",
    "platform": "FanCode",
    "channelName": "CCC vs DLC",
    "subText": "Live tv guide",
    "startTime": "",
    "drm_licence": "",
    "ownerInfo": "Stream provided by public source",
    "thumbnail": "https://www.fancode.com/skillup-uploads/cms-media/137303_5711_DL_CHI_fc-Web_1759932203337.jpg",
    "channelUrl": "https://in-mc-fdlive.fancode.com/mumbai/137303_english_hls_54e55d024e81073ta-di_h264/index.m3u8",
    "match_id": 137303
  },
  {
    "channelNumber": 133957,
    "linkType": "app",
    "platform": "FanCode",
    "channelName": "TW vs VWW",
    "subText": "Live tv guide",
    "startTime": "",
    "drm_licence": "",
    "ownerInfo": "Stream provided by public source",
    "thumbnail": "https://www.fancode.com/skillup-uploads/cms-media/Women's-National-Cricket-League_old_v2_1758034980092.jpg",
    "channelUrl": "https://in-mc-fdlive.fancode.com/mumbai/133957_english_hls_5def3890143213ta-di_h264/index.m3u8",
    "match_id": 133957
  },
  {
    "channelNumber": 137426,
    "linkType": "app",
    "platform": "FanCode",
    "channelName": "VK vs MRT",
    "subText": "Live tv guide",
    "startTime": "",
    "drm_licence": "",
    "ownerInfo": "Stream provided by public source",
    "thumbnail": "https://www.fancode.com/skillup-uploads/cms-media/137426_5719_MRT_VCK_fc-Web.jpg",
    "channelUrl": "https://in-mc-fdlive.fancode.com/mumbai/137426_english_hls_1783e3951747655ta-di_h264/index.m3u8",
    "match_id": 137426
  },
  {
    "channelNumber": 1389,
    "platform": "CricHD",
    "linkType": "app",
    "channelName": "Server 2",
    "subText": "Live tv guide",
    "startTime": "",
    "ownerInfo": "Stream provided by public source",
    "channelUrl": "https://d15.epicquesthero.com:999/hls/willowusa.m3u8?md5=0GrUG8_MR2K3eqdDDUgWfg&expires=1760060361",
    "thumbnail": "https://gitlab.com/ranginfotech89/ipl_data_api/-/raw/main/stream_categories/cricket_league_vectors/all_live_streaming_inonly.png"
  },
  {
    "channelNumber": 5535,
    "platform": "CricHD",
    "linkType": "app",
    "channelName": "Server 1",
    "subText": "Live tv guide",
    "startTime": "",
    "ownerInfo": "Stream provided by public source",
    "channelUrl": "https://d15.epicquesthero.com:999/hls/star1in.m3u8?md5=pJruPFqXeHkt7sxO5mozow&expires=1760060361",
    "thumbnail": "https://gitlab.com/ranginfotech89/ipl_data_api/-/raw/main/stream_categories/cricket_league_vectors/all_live_streaming_inonly.png"
  }
]