[
  {
    "channelNumber": 1090505345,
    "linkType": "app",
    "platform": "SonyLiv",
    "channelName": "Bundesliga 2025-26",
    "subText": "Live Streaming Now",
    "startTime": "",
    "drm_licence": "",
    "ownerInfo": "Stream provided by public source",
    "thumbnail": "https://origin-staticv2.sonyliv.com/videoasset_images/manage_file/1000015686/1772263685247596_BLIGA_26_MD24_VfB-Stuttgart-vs-VfL-Wolfsburg_landscape_thumb.jpg",
    "channelUrl": "https://sonydaimenew.akamaized.net/hls/live/2094588/DAI04ME-V3/std_lrh-800300010.m3u8?hdnea=exp=1772421041~acl=/*~id=74992572353830898744119437439083~hmac=ca22aadd9c775c1f5ddce24fa527253107d155a1282287a50647025a57a29f71",
    "match_id": "1090505345_ENG",
    "category": "football"
  },
  {
    "channelNumber": 131083,
    "linkType": "app",
    "platform": "FanCode",
    "channelName": "VCF vs COL",
    "subText": "Live Streaming Now",
    "startTime": "",
    "drm_licence": "",
    "ownerInfo": "Stream provided by public source",
    "thumbnail": "https://www.fancode.com/skillup-uploads/cms-media/131083_5427_VAL_OSN_FC-Web.png",
    "channelUrl": "https://in-mc-fdlive.fancode.com/mumbai/131083_english_hls_39041d3f9561489_1ta-di_h264/index.m3u8",
    "match_id": 131083,
    "category": "football"
  },
  {
    "channelNumber": 140824,
    "linkType": "app",
    "platform": "FanCode",
    "channelName": "RS vs DLC - LH",
    "subText": "Live Streaming Now",
    "startTime": "",
    "drm_licence": "",
    "ownerInfo": "Stream provided by public source",
    "thumbnail": "https://images.fancode.com/aig/match/v1772160982911/140824_CASACARDS_APP.png",
    "channelUrl": "https://in-mc-flive.fancode.com/mumbai/140824_english_hls_63a18503a8455_1ta-di_h264/index.m3u8",
    "match_id": 140824,
    "category": "football"
  },
  {
    "channelNumber": 140451,
    "linkType": "app",
    "platform": "FanCode",
    "channelName": "MCF vs NUF - I",
    "subText": "Live Streaming Now",
    "startTime": "",
    "drm_licence": "",
    "ownerInfo": "Stream provided by public source",
    "thumbnail": "https://www.fancode.com/skillup-uploads/cms-media/140451_5956_MCFC_NEUFC_fc-web_1772229182804.jpg",
    "channelUrl": "https://in-mc-flive.fancode.com/mumbai/140451_bengali_hls_4384a4f9dc22175_1ta-di_h264/index.m3u8",
    "match_id": 140451,
    "category": "football"
  },
  {
    "channelNumber": 140451,
    "linkType": "app",
    "platform": "FanCode",
    "channelName": "MCF vs NUF - I - Malayalam",
    "subText": "Live Streaming Now",
    "startTime": "",
    "drm_licence": "",
    "ownerInfo": "Stream provided by public source",
    "thumbnail": "https://www.fancode.com/skillup-uploads/cms-media/140451_5956_MCFC_NEUFC_fc-web_1772229182804.jpg",
    "channelUrl": "https://in-mc-flive.fancode.com/mumbai/140451_malayalam_hls_8d4392931848726_1ta-di_h264/index.m3u8",
    "match_id": 140451,
    "category": "football"
  },
  {
    "channelNumber": 140451,
    "linkType": "app",
    "platform": "FanCode",
    "channelName": "MCF vs NUF - I - Hindi",
    "subText": "Live Streaming Now",
    "startTime": "",
    "drm_licence": "",
    "ownerInfo": "Stream provided by public source",
    "thumbnail": "https://www.fancode.com/skillup-uploads/cms-media/140451_5956_MCFC_NEUFC_fc-web_1772229182804.jpg",
    "channelUrl": "https://in-mc-flive.fancode.com/mumbai/140451_hindi_hls_36a17ba90e50965_1ta-di_h264/index.m3u8",
    "match_id": 140451,
    "category": "football"
  },
  {
    "channelNumber": 140451,
    "linkType": "app",
    "platform": "FanCode",
    "channelName": "MCF vs NUF - I",
    "subText": "Live Streaming Now",
    "startTime": "",
    "drm_licence": "",
    "ownerInfo": "Stream provided by public source",
    "thumbnail": "https://www.fancode.com/skillup-uploads/cms-media/140451_5956_MCFC_NEUFC_fc-web_1772229182804.jpg",
    "channelUrl": "https://in-mc-flive.fancode.com/mumbai/140451_english_hls_dd1e27ec0836523_1ta-di_h264/index.m3u8",
    "match_id": 140451,
    "category": "football"
  },
  {
    "channelNumber": 131086,
    "linkType": "app",
    "platform": "FanCode",
    "channelName": "ECF vs RE - L",
    "subText": "Live Streaming Now",
    "startTime": "",
    "drm_licence": "",
    "ownerInfo": "Stream provided by public source",
    "thumbnail": "https://www.fancode.com/skillup-uploads/cms-media/131086_5427_ELC_ESL_FC-Web.png",
    "channelUrl": "https://in-mc-flive.fancode.com/mumbai/131086_english_hls_36546f8a7656011_1ta-di_h264/index.m3u8",
    "match_id": 131086,
    "category": "football"
  },
  {
    "channelNumber": 70,
    "platform": "FanCode",
    "linkType": "app",
    "channelName": "Football Stream 1",
    "subText": "Live Streaming Now",
    "startTime": "",
    "ownerInfo": "Stream provided by public source",
    "channelUrl": "https://dmitwlvvll.cdn.mangomolo.com/dubaisportshd/smil:dubaisportshd.smil/index.m3u8",
    "thumbnail": "https://gitlab.com/ranginfotech89/ipl_data_api/-/raw/main/stream_categories/cricket_league_vectors/football_new.png"
  }
]