[
  {
    "channelNumber": 139277,
    "linkType": "app",
    "platform": "FanCode",
    "channelName": "UU2 vs CPU",
    "subText": "Live Streaming Now",
    "startTime": "",
    "drm_licence": "",
    "ownerInfo": "Stream provided by public source",
    "thumbnail": "https://www.fancode.com/skillup-uploads/cms-media/Uzbekistan-U23_vs_ChinaPR_fc-web.jpg",
    "channelUrl": "https://in-mc-fdlive.fancode.com/mumbai/139277_english_hls_de1c6a34da85554_1ta-di_h264/index.m3u8",
    "match_id": 139277,
    "category": "football"
  },
  {
    "channelNumber": 131025,
    "linkType": "app",
    "platform": "FanCode",
    "channelName": "RM vs LL2",
    "subText": "Live Streaming Now",
    "startTime": "",
    "drm_licence": "",
    "ownerInfo": "Stream provided by public source",
    "thumbnail": "https://www.fancode.com/skillup-uploads/cms-media/131025_5427_RM_LE_fc-Web.png",
    "channelUrl": "https://in-mc-fdlive.fancode.com/mumbai/131025_english_hls_ce5579a68110873_1ta-di_h264/index.m3u8",
    "match_id": 131025,
    "category": "football"
  },
  {
    "channelNumber": 139914,
    "linkType": "app",
    "platform": "FanCode",
    "channelName": "CCF vs LCF",
    "subText": "Live Streaming Now",
    "startTime": "",
    "drm_licence": "",
    "ownerInfo": "Stream provided by public source",
    "thumbnail": "https://images.fancode.com/aig/match/v1/139914_CASACARDS_APP.png",
    "channelUrl": "https://in-mc-fdlive.fancode.com/mumbai/139914_english_hls_ec0f740f6e39831_1ta-di_h264/index.m3u8",
    "match_id": 139914,
    "category": "football"
  },
  {
    "channelNumber": 70,
    "platform": "FanCode",
    "linkType": "app",
    "channelName": "Football Stream 1",
    "subText": "Live Streaming Now",
    "startTime": "",
    "ownerInfo": "Stream provided by public source",
    "channelUrl": "https://dmitwlvvll.cdn.mangomolo.com/dubaisportshd/smil:dubaisportshd.smil/index.m3u8",
    "thumbnail": "https://gitlab.com/ranginfotech89/ipl_data_api/-/raw/main/stream_categories/cricket_league_vectors/football_new.png"
  }
]