[
  {
    "channelNumber": 1090494617,
    "linkType": "app",
    "platform": "SonyLiv",
    "channelName": "DP World Asia Cup Rising Stars Men's 2025",
    "subText": "Live Streaming Now",
    "startTime": "",
    "drm_licence": "",
    "ownerInfo": "Stream provided by public source",
    "thumbnail": "https://origin-staticv2.sonyliv.com/videoasset_images/manage_file/1000011205/1763036732581604_AsiaCup_PakA_vs_OMA_12nov_live_landscape_thumb.jpg",
    "channelUrl": "https://sonydaimenew.akamaized.net/hls/live/2037140/DAI20-criclive/std_lrh-800300010.m3u8?hdnea=exp=1763142750~acl=/*~id=24674192940068645538938601254578~hmac=5853716ee6b571a79f7220ff5888869add6eb0ca7bd2727329672b72940b4cc3",
    "match_id": "1090494617_ENG"
  },
  {
    "channelNumber": 138022,
    "linkType": "app",
    "platform": "FanCode",
    "channelName": "MYA vs TRE",
    "subText": "Live tv guide",
    "startTime": "",
    "drm_licence": "",
    "ownerInfo": "Stream provided by public source",
    "thumbnail": "https://www.fancode.com/skillup-uploads/cms-media/138022_5753_TLS_MYN_FC-Web.jpg",
    "channelUrl": "https://in-mc-fdlive.fancode.com/mumbai/138022_english_hls_51d7ece6da35437_1ta-di_h264/index.m3u8",
    "match_id": 138022
  },
  {
    "channelNumber": 134025,
    "linkType": "app",
    "platform": "FanCode",
    "channelName": "QUE vs WAS",
    "subText": "Live tv guide",
    "startTime": "",
    "drm_licence": "",
    "ownerInfo": "Stream provided by public source",
    "thumbnail": "https://www.fancode.com/skillup-uploads/cms-media/134025_5609_WAU_QUN_fc-Web.jpg",
    "channelUrl": "https://in-mc-fdlive.fancode.com/mumbai/134025_english_hls_f309bf133729011_1ta-di_h264/index.m3u8",
    "match_id": 134025
  },
  {
    "channelNumber": 138237,
    "linkType": "app",
    "platform": "FanCode",
    "channelName": "IRE vs BIT",
    "subText": "Live tv guide",
    "startTime": "",
    "drm_licence": "",
    "ownerInfo": "Stream provided by public source",
    "thumbnail": "https://www.fancode.com/skillup-uploads/cms-media/BAN-vs-IRE_old-match-card.png",
    "channelUrl": "https://in-mc-fdlive.fancode.com/mumbai/138237_english_hls_3626c1011428485_1ta-di_h264/index.m3u8",
    "match_id": 138237
  },
  {
    "channelNumber": 70,
    "platform": "FanCode",
    "linkType": "web",
    "channelName": "Server 1",
    "subText": "Live tv guide",
    "startTime": "",
    "ownerInfo": "Stream provided by public source",
    "channelUrl": "",
    "thumbnail": "https://gitlab.com/ranginfotech89/ipl_data_api/-/raw/main/stream_categories/cricket_league_vectors/all_live_streaming_inonly.png"
  },
  {
    "channelNumber": 70,
    "platform": "FanCode",
    "linkType": "web",
    "channelName": "Server 2",
    "subText": "Live tv guide",
    "startTime": "",
    "ownerInfo": "Stream provided by public source",
    "channelUrl": "",
    "thumbnail": "https://gitlab.com/ranginfotech89/ipl_data_api/-/raw/main/stream_categories/cricket_league_vectors/all_live_streaming_inonly.png"
  },
  {
    "channelNumber": 70,
    "platform": "FanCode",
    "linkType": "web",
    "channelName": "Server 3",
    "subText": "Live tv guide",
    "startTime": "",
    "ownerInfo": "Stream provided by public source",
    "channelUrl": "",
    "thumbnail": "https://gitlab.com/ranginfotech89/ipl_data_api/-/raw/main/stream_categories/cricket_league_vectors/all_live_streaming_inonly.png"
  },
  {
    "channelNumber": 70,
    "platform": "FanCode",
    "linkType": "web",
    "channelName": "Server 4",
    "subText": "Live tv guide",
    "startTime": "",
    "ownerInfo": "Stream provided by public source",
    "channelUrl": "",
    "thumbnail": "https://gitlab.com/ranginfotech89/ipl_data_api/-/raw/main/stream_categories/cricket_league_vectors/all_live_streaming_inonly.png"
  },
  {
    "channelNumber": 70,
    "platform": "FanCode",
    "linkType": "web",
    "channelName": "Server 5",
    "subText": "Live tv guide",
    "startTime": "",
    "ownerInfo": "Stream provided by public source",
    "channelUrl": "",
    "thumbnail": "https://gitlab.com/ranginfotech89/ipl_data_api/-/raw/main/stream_categories/cricket_league_vectors/all_live_streaming_inonly.png"
  },
  {
    "channelNumber": 70,
    "platform": "FanCode",
    "linkType": "web",
    "channelName": "Server 6",
    "subText": "Live tv guide",
    "startTime": "",
    "ownerInfo": "Stream provided by public source",
    "channelUrl": "",
    "thumbnail": "https://gitlab.com/ranginfotech89/ipl_data_api/-/raw/main/stream_categories/cricket_league_vectors/all_live_streaming_inonly.png"
  },
  {
    "channelNumber": 70,
    "platform": "FanCode",
    "linkType": "web",
    "channelName": "Server 7",
    "subText": "Live tv guide",
    "startTime": "",
    "ownerInfo": "Stream provided by public source",
    "channelUrl": "",
    "thumbnail": "https://gitlab.com/ranginfotech89/ipl_data_api/-/raw/main/stream_categories/cricket_league_vectors/all_live_streaming_inonly.png"
  },
  {
    "channelNumber": 70,
    "platform": "FanCode",
    "linkType": "web",
    "channelName": "Server 8",
    "subText": "Live tv guide",
    "startTime": "",
    "ownerInfo": "Stream provided by public source",
    "channelUrl": "",
    "thumbnail": "https://gitlab.com/ranginfotech89/ipl_data_api/-/raw/main/stream_categories/cricket_league_vectors/all_live_streaming_inonly.png"
  },
  {
    "channelNumber": 70,
    "platform": "FanCode",
    "linkType": "web",
    "channelName": "Server 9",
    "subText": "Live tv guide",
    "startTime": "",
    "ownerInfo": "Stream provided by public source",
    "channelUrl": "",
    "thumbnail": "https://gitlab.com/ranginfotech89/ipl_data_api/-/raw/main/stream_categories/cricket_league_vectors/all_live_streaming_inonly.png"
  },
  {
    "channelNumber": 70,
    "platform": "FanCode",
    "linkType": "web",
    "channelName": "Server 10",
    "subText": "Live tv guide",
    "startTime": "",
    "ownerInfo": "Stream provided by public source",
    "channelUrl": "",
    "thumbnail": "https://gitlab.com/ranginfotech89/ipl_data_api/-/raw/main/stream_categories/cricket_league_vectors/all_live_streaming_inonly.png"
  },
  {
    "channelNumber": 70,
    "platform": "FanCode",
    "linkType": "web",
    "channelName": "Server 11",
    "subText": "Live tv guide",
    "startTime": "",
    "ownerInfo": "Stream provided by public source",
    "channelUrl": "",
    "thumbnail": "https://gitlab.com/ranginfotech89/ipl_data_api/-/raw/main/stream_categories/cricket_league_vectors/all_live_streaming_inonly.png"
  },
  {
    "channelNumber": 70,
    "platform": "FanCode",
    "linkType": "web",
    "channelName": "Server 12",
    "subText": "Live tv guide",
    "startTime": "",
    "ownerInfo": "Stream provided by public source",
    "channelUrl": "",
    "thumbnail": "https://gitlab.com/ranginfotech89/ipl_data_api/-/raw/main/stream_categories/cricket_league_vectors/all_live_streaming_inonly.png"
  }
]