[
  {
    "channelNumber": 1090529620,
    "linkType": "app",
    "platform": "SonyLiv",
    "channelName": "Bundesliga 2025-26",
    "subText": "Live Streaming Now",
    "startTime": "",
    "drm_licence": "",
    "ownerInfo": "Stream provided by public source",
    "thumbnail": "https://origin-staticv2.sonyliv.com/videoasset_images/manage_file/1000017551/1777372597018475_Bundesliga_2025-26_MD-32_St-Pauli-vs-Mainz_landscape_thumb.jpg",
    "channelUrl": "https://sonydaimenew.akamaized.net/hls/live/2105080/StPauli_0305/ENG/std_lrh-800300010.m3u8?hdnea=exp=1777863372~acl=/*~id=43761752554602764642489481606718~hmac=6ba0adf42d9e8ffbe903f78ef24a3d6d70aec042c021a9720afedd18f67bcbae",
    "match_id": "1090529620_ENG",
    "category": "football"
  },
  {
    "channelNumber": 1090529605,
    "linkType": "app",
    "platform": "SonyLiv",
    "channelName": "Star Cement Indian Football League 2025-26",
    "subText": "Live Streaming Now",
    "startTime": "",
    "drm_licence": "",
    "ownerInfo": "Stream provided by public source",
    "thumbnail": "https://origin-staticv2.sonyliv.com/videoasset_images/manage_file/1000017695/1777814290883144_IFL26_Diamond-Harbour-FC-vs-Sreenidi-Deccan-FC_landscape_thumb.jpg",
    "channelUrl": "https://sonydaimenew.akamaized.net/hls/live/2037142/INDIAN_F0305/ENG/std_lrh-800300010.m3u8?hdnea=exp=1777863372~acl=/*~id=43761752554602764642489481606718~hmac=6ba0adf42d9e8ffbe903f78ef24a3d6d70aec042c021a9720afedd18f67bcbae",
    "match_id": "1090529605_ENG",
    "category": "football"
  },
  {
    "channelNumber": 1090529621,
    "linkType": "app",
    "platform": "SonyLiv",
    "channelName": "Bundesliga 2025-26",
    "subText": "Live Streaming Now",
    "startTime": "",
    "drm_licence": "",
    "ownerInfo": "Stream provided by public source",
    "thumbnail": "https://origin-staticv2.sonyliv.com/videoasset_images/manage_file/1000017551/1777372816364475_Bundesliga_2025-26_MD-32_Borussia-Mgladbach-vs-Dortmund_landscape_thumb.jpg",
    "channelUrl": "https://sonydaimenew.akamaized.net/hls/live/2018458/BLIGA_Bo0305/ENG/std_lrh-800300010.m3u8?hdnea=exp=1777863372~acl=/*~id=43761752554602764642489481606718~hmac=6ba0adf42d9e8ffbe903f78ef24a3d6d70aec042c021a9720afedd18f67bcbae",
    "match_id": "1090529621_ENG",
    "category": "football"
  },
  {
    "channelNumber": 141966,
    "linkType": "app",
    "platform": "FanCode",
    "channelName": "BW vs BMW",
    "subText": "Live Streaming Now",
    "startTime": "",
    "drm_licence": "",
    "ownerInfo": "Stream provided by public source",
    "thumbnail": "https://www.fancode.com/skillup-uploads/cms-media/Barcelona-W-vs-Bayern-Munich-W_fc-web.jpg",
    "channelUrl": "https://in-mc-fblive.fancode.com/mumbai/141966_english_hls_f7610d9c8684934_1ta-di_h264/index.m3u8",
    "match_id": 141966,
    "category": "football"
  },
  {
    "channelNumber": 131166,
    "linkType": "app",
    "platform": "FanCode",
    "channelName": "GCF vs RVL",
    "subText": "Live Streaming Now",
    "startTime": "",
    "drm_licence": "",
    "ownerInfo": "Stream provided by public source",
    "thumbnail": "https://www.fancode.com/skillup-uploads/cms-media/131166_5427_GEF_RVL_FC-Web.png",
    "channelUrl": "https://in-mc-fdlive.fancode.com/mumbai/131166_english_hls_188466d0a52451_1ta-di_h264/index.m3u8",
    "match_id": 131166,
    "category": "football"
  },
  {
    "channelNumber": 142173,
    "linkType": "app",
    "platform": "FanCode",
    "channelName": "LCW vs CWS",
    "subText": "Live Streaming Now",
    "startTime": "",
    "drm_licence": "",
    "ownerInfo": "Stream provided by public source",
    "thumbnail": "https://www.fancode.com/skillup-uploads/cms-media/142173_5826_LEI-W_CHE_FC-Web.jpg",
    "channelUrl": "https://in-mc-fblive.fancode.com/mumbai/142173_english_hls_517da3a2fd97253_1ta-di_h264/index.m3u8",
    "match_id": 142173,
    "category": "football"
  },
  {
    "channelNumber": 70,
    "platform": "FanCode",
    "linkType": "app",
    "channelName": "Football Stream 1",
    "subText": "Live Streaming Now",
    "startTime": "",
    "ownerInfo": "Stream provided by public source",
    "channelUrl": "https://dmitwlvvll.cdn.mangomolo.com/dubaisportshd/smil:dubaisportshd.smil/index.m3u8",
    "thumbnail": "https://gitlab.com/ranginfotech89/ipl_data_api/-/raw/main/stream_categories/cricket_league_vectors/football_new.png"
  }
]